[{"id":"0b86e0f3-9fb4-4da2-b8ed-0154c5f457a1","name":"نرم\u200cافزار","slug":"software","description":"نرم\u200cافزارهای تخصصی و کاربردی","created_at":"2025-09-24T08:42:03.012Z"},{"id":"14f3de42-f3ed-481d-98c3-c71db3305a77","name":"آموزش","slug":"education","description":"پلتفرم\u200cهای آموزشی و یادگیری","created_at":"2025-09-24T08:42:03.088Z"},{"id":"259eb2c5-a54d-4c51-a834-8eccb229cad7","name":"پلتفرم ویدئو","slug":"svod","description":"پلتفرم\u200cهای مختلف ویدئو و پخش زنده","created_at":"2025-09-24T08:42:03.050Z"},{"id":"54510514-e720-4591-82e9-f1750bc80dd2","name":"پکیج های سئو","slug":"seo","description":"ابزارهای بهینه\u200cسازی موتورهای جستجو","created_at":"2025-09-24T08:42:02.930Z"},{"id":"6d3f80c7-75cf-43c7-bde8-afe6dbba4abb","name":"جدید","slug":"cloud","description":"جدیدترین سرویس\u200cها و محصولات","created_at":"2025-09-24T08:42:03.125Z"},{"id":"a1e41941-cdf9-4980-9c52-cb42a105d3c7","name":"موسیقی","slug":"music","description":"پلتفرم\u200cهای پخش موسیقی و صوت","created_at":"2025-09-24T08:42:02.890Z"},{"id":"bcc5c8fc-8ecc-43cf-857e-1c03391da965","name":"گرافیک","slug":"creative","description":"نرم\u200cافزارهای طراحی و گرافیک","created_at":"2025-09-24T08:42:02.842Z"},{"id":"cd39c273-6a24-403d-8a0c-6cfc0e660495","name":"هوش مصنوعی","slug":"ai","description":"ابزارهای هوش مصنوعی و یادگیری ماشین","created_at":"2025-09-24T08:42:02.967Z"}]